dog/__init__.py
dog/client.py
dog/models.py
dog.py-0.2.0.dist-info/LICENSE
dog.py-0.2.0.dist-info/WHEEL
dog.py-0.2.0.dist-info/METADATA
dog.py-0.2.0.dist-info/RECORD
