Metadata-Version: 2.1
Name: dog.py
Version: 0.2.0
Summary: An API wrapper for https://thedogapi.com/ that covers the full API.
License: MIT
Author: ToxicKidz
Author-email: 78174417+ToxicKidz@users.noreply.github.com
Requires-Python: >=3.6
Classifier: License :: OSI Approved :: MIT License
Classifier: Programming Language :: Python :: 3
Classifier: Programming Language :: Python :: 3.6
Classifier: Programming Language :: Python :: 3.7
Classifier: Programming Language :: Python :: 3.8
Classifier: Programming Language :: Python :: 3.9
Requires-Dist: requests (>=2.25.1,<3.0.0)
